{
  "project_info": {
    "project_number": "625176705277",
    "project_id": "projekconsultant-b3391",
    "storage_bucket": "projekconsultant-b3391.appspot.com"
  },
  "client": [
    {
      "client_info": {
        "mobilesdk_app_id": "1:625176705277:android:756d50d65d33476e3e2694",
        "android_client_info": {
          "package_name": "com.example.projekconsultant"
        }
      },
      "oauth_client": [],
      "api_key": [
        {
          "current_key": "AIzaSyAsU79eIKKhyPPQtS7NidoFW48rWMqLV8o"
        }
      ],
      "services": {
        "appinvite_service": {
          "other_platform_oauth_client": []
        }
      }
    }
  ],
  "configuration_version": "1"
}